sass.py
django_sass_processor_dart_sass-0.0.1.dist-info/LICENSE.txt
django_sass_processor_dart_sass-0.0.1.dist-info/METADATA
django_sass_processor_dart_sass-0.0.1.dist-info/WHEEL
django_sass_processor_dart_sass-0.0.1.dist-info/top_level.txt
django_sass_processor_dart_sass-0.0.1.dist-info/RECORD
