Metadata-Version: 2.1
Name: django-sass-processor-dart-sass
Version: 0.0.1
Summary: A drop-in replacement for sass for use with django-sass-processor that uses dart sass rather than libsass
Author-email: Greg Kempe <greg@laws.africa>
Project-URL: Homepage, https://github.com/laws-africa/django-sass-processor-dart-sass
Project-URL: Bug Tracker, https://github.com/laws-africa/django-sass-processor-dart-sass/issues
Classifier: Programming Language :: Python :: 3
Classifier: License :: OSI Approved :: MIT License
Classifier: Operating System :: OS Independent
Requires-Python: >=3.7
License-File: LICENSE.txt
